phylodeep_data_BDEI_small/__init__.py
phylodeep_data_BDEI_small/ci_computation/predicted_values/BDEI_SMALL_CNN.csv.gz
phylodeep_data_BDEI_small/ci_computation/predicted_values/BDEI_SMALL_FFNN.csv.gz
phylodeep_data_BDEI_small/ci_computation/target_values/BDEI_SMALL.csv.gz
phylodeep_data_BDEI_small-0.0.1.dist-info/METADATA
phylodeep_data_BDEI_small-0.0.1.dist-info/WHEEL
phylodeep_data_BDEI_small-0.0.1.dist-info/top_level.txt
phylodeep_data_BDEI_small-0.0.1.dist-info/RECORD
