Metadata-Version: 2.1
Name: phylodeep-data-BDEI-small
Version: 0.0.1
Summary: Data for phylodeep package
Home-page: https://github.com/evolbioinfo/deepphylo
Author: Jakub Voznica, Anna Zhukova
Author-email: jakub.voznica@pasteur.fr
License: UNKNOWN
Platform: UNKNOWN
